scrappy/__init__.py
scrappy/agent_config.py
scrappy/orchestrator_adapter.py
scrappy/undo.py
scrappy/agent_tools/__init__.py
scrappy/agent_tools/constants.py
scrappy/agent_tools/registry_factory.py
scrappy/agent_tools/components/__init__.py
scrappy/agent_tools/components/command_advisor.py
scrappy/agent_tools/components/command_security.py
scrappy/agent_tools/components/output_collector.py
scrappy/agent_tools/components/output_parser.py
scrappy/agent_tools/components/sandboxed_runner.py
scrappy/agent_tools/components/search_output_parser.py
scrappy/agent_tools/components/subprocess_runner.py
scrappy/agent_tools/components/text_search.py
scrappy/agent_tools/components/text_search_factory.py
scrappy/agent_tools/formatters/__init__.py
scrappy/agent_tools/formatters/output_formatter.py
scrappy/agent_tools/protocols/__init__.py
scrappy/agent_tools/tools/__init__.py
scrappy/agent_tools/tools/base.py
scrappy/agent_tools/tools/command_tool.py
scrappy/agent_tools/tools/control_tools.py
scrappy/agent_tools/tools/file_tools.py
scrappy/agent_tools/tools/git_tools.py
scrappy/agent_tools/tools/registry.py
scrappy/agent_tools/tools/search_tools.py
scrappy/agent_tools/tools/semantic_search_tool.py
scrappy/agent_tools/tools/task_tools.py
scrappy/agent_tools/tools/testing_tools.py
scrappy/agent_tools/tools/web_tools.py
scrappy/cli/__init__.py
scrappy/cli/agent_manager.py
scrappy/cli/cache_manager.py
scrappy/cli/cli_config.py
scrappy/cli/codebase.py
scrappy/cli/command_history.py
scrappy/cli/command_router.py
scrappy/cli/commands.py
scrappy/cli/config_factory.py
scrappy/cli/context_commands.py
scrappy/cli/core.py
scrappy/cli/display.py
scrappy/cli/display_manager.py
scrappy/cli/display_rich.py
scrappy/cli/exceptions.py
scrappy/cli/input_capture.py
scrappy/cli/input_handler.py
scrappy/cli/interactive.py
scrappy/cli/interactive_banner.py
scrappy/cli/io_interface.py
scrappy/cli/logging.py
scrappy/cli/mode_utils.py
scrappy/cli/output.py
scrappy/cli/output_bridge.py
scrappy_ai-1.2.0.dist-info/licenses/LICENSE.md
scrappy_ai-1.2.0.dist-info/METADATA
scrappy_ai-1.2.0.dist-info/WHEEL
scrappy_ai-1.2.0.dist-info/entry_points.txt
scrappy_ai-1.2.0.dist-info/top_level.txt
scrappy_ai-1.2.0.dist-info/RECORD
