Metadata-Version: 2.4
Name: scrappy-ai
Version: 1.2.0
Summary: A context-aware coding assistant for everyone. Students, learners, anyone who doesn't want to pay for subscriptions.
Author: Scrappy Contributors
License: MIT
Project-URL: Homepage, https://github.com/HakAl/scrappy
Project-URL: Repository, https://github.com/HakAl/scrappy
Project-URL: Issues, https://github.com/HakAl/scrappy/issues
Keywords: llm,ai,orchestration,multi-provider,cli
Classifier: Development Status :: 5 - Production/Stable
Classifier: Environment :: Console
Classifier: Intended Audience :: Developers
Classifier: License :: OSI Approved :: MIT License
Classifier: Programming Language :: Python :: 3
Classifier: Programming Language :: Python :: 3.10
Classifier: Programming Language :: Python :: 3.11
Classifier: Programming Language :: Python :: 3.12
Classifier: Topic :: Software Development :: Libraries :: Python Modules
Classifier: Topic :: Scientific/Engineering :: Artificial Intelligence
Requires-Python: >=3.11
License-File: LICENSE.md
Requires-Dist: instructor>=1.7.0
Requires-Dist: litellm>=1.80.10
Requires-Dist: python-dotenv>=1.0.0
Requires-Dist: openai>=1.0.0
Requires-Dist: click>=8.0.0
Requires-Dist: rich>=14.2.0
Requires-Dist: lancedb>=0.5.0
Requires-Dist: fastembed>=0.2.0
Requires-Dist: fasteners>=0.19
Requires-Dist: tantivy>=0.21.0; sys_platform != "win32"
Requires-Dist: pyperclip>=1.11.0
Requires-Dist: textual>=0.47.0
Requires-Dist: langgraph>=0.2.0
Requires-Dist: langfuse<3.0.0,>=2.0.0
Requires-Dist: docker>=7.0.0
Provides-Extra: dev
Requires-Dist: pytest>=7.0.0; extra == "dev"
Requires-Dist: pytest-cov>=4.0.0; extra == "dev"
Requires-Dist: pytest-asyncio>=0.21.0; extra == "dev"
Requires-Dist: pytest-recording>=0.13.0; extra == "dev"
Requires-Dist: vcrpy>=8.0.0; extra == "dev"
Requires-Dist: black>=23.0.0; extra == "dev"
Requires-Dist: ruff>=0.1.0; extra == "dev"
Requires-Dist: mypy>=1.0.0; extra == "dev"
Requires-Dist: towncrier>=23.0.0; extra == "dev"
Provides-Extra: nomic
Requires-Dist: gpt4all>=2.0.0; extra == "nomic"
Provides-Extra: jina
Requires-Dist: sentence-transformers>=2.2.0; extra == "jina"
Provides-Extra: all-embeddings
Requires-Dist: gpt4all>=2.0.0; extra == "all-embeddings"
Requires-Dist: sentence-transformers>=2.2.0; extra == "all-embeddings"
Dynamic: license-file
